{
  "headers": {
    "Alt-Svc": [
      "h3=\":443\"; ma=86400"
    ],
    "Cache-Control": [
      "no-cache"
    ],
    "Cf-Cache-Status": [
      "DYNAMIC"
    ],
    "Cf-Ray": [
      "9f14d80bfbe7d29b-NRT"
    ],
    "Content-Type": [
      "text/event-stream"
    ],
    "Date": [
      "Fri, 24 Apr 2026 11:42:24 GMT"
    ],
    "Nel": [
      "{\"report_to\":\"cf-nel\",\"success_fraction\":0.0,\"max_age\":604800}"
    ],
    "Report-To": [
      "{\"group\":\"cf-nel\",\"max_age\":604800,\"endpoints\":[{\"url\":\"https://a.nel.cloudflare.com/report/v4?s=W31SKGaYCQxQn8V9RN7WIapQCh7eV3k%2FW%2Bf7bqEW1InfamiCg9V0b2VEPL1GtHVjCcnwPwzeHgfIIoiZOW95%2FsfrKbIcHqlbbITxLBTeTqv4GU86kLrESoBpSIFhxu%2B5jA%3D%3D\"}]}"
    ],
    "Server": [
      "cloudflare"
    ],
    "Server-Timing": [
      "cfCacheStatus;desc=\"DYNAMIC\"",
      "cfEdge;dur=74,cfOrigin;dur=4429"
    ],
    "X-Oneapi-Request-Id": [
      "20260424114219611137295MiId129A"
    ]
  },
  "status_code": 200
}